CHANGELOG.md
LICENSE
MANIFEST.in
Makefile
README.md
setup.cfg
setup.py
tox.ini
tests/test_attached_users.py
tests/test_celery.py
tests/test_run.py
tests/test_scheduled_celery.py
wc_django_envoyer.egg-info/PKG-INFO
wc_django_envoyer.egg-info/SOURCES.txt
wc_django_envoyer.egg-info/dependency_links.txt
wc_django_envoyer.egg-info/requires.txt
wc_django_envoyer.egg-info/top_level.txt
wcd_envoyer/__init__.py
wcd_envoyer/apps.py
wcd_envoyer/conf.py
wcd_envoyer/const.py
wcd_envoyer/events.py
wcd_envoyer/exceptions.py
wcd_envoyer/shortcuts.py
wcd_envoyer/signals.py
wcd_envoyer/admin/__init__.py
wcd_envoyer/admin/channels.py
wcd_envoyer/admin/forms.py
wcd_envoyer/admin/messages.py
wcd_envoyer/admin/templates.py
wcd_envoyer/admin/utils.py
wcd_envoyer/channels/__init__.py
wcd_envoyer/channels/backend.py
wcd_envoyer/channels/forms.py
wcd_envoyer/channels/registry_base.py
wcd_envoyer/channels/renderers.py
wcd_envoyer/channels/backends/__init__.py
wcd_envoyer/channels/backends/console.py
wcd_envoyer/channels/backends/django_sendmail.py
wcd_envoyer/contrib/__init__.py
wcd_envoyer/contrib/attached_users/__init__.py
wcd_envoyer/contrib/attached_users/admin.py
wcd_envoyer/contrib/attached_users/apps.py
wcd_envoyer/contrib/attached_users/models.py
wcd_envoyer/contrib/attached_users/migrations/0001_initial.py
wcd_envoyer/contrib/attached_users/migrations/__init__.py
wcd_envoyer/contrib/attached_users/services/__init__.py
wcd_envoyer/contrib/attached_users/services/sender.py
wcd_envoyer/contrib/celery/__init__.py
wcd_envoyer/contrib/celery/shortcuts.py
wcd_envoyer/contrib/celery/tasks.py
wcd_envoyer/contrib/celery/services/__init__.py
wcd_envoyer/contrib/celery/services/sender.py
wcd_envoyer/contrib/pxd_actions_tracker/__init__.py
wcd_envoyer/contrib/pxd_actions_tracker/apps.py
wcd_envoyer/contrib/pxd_actions_tracker/handlers.py
wcd_envoyer/contrib/pxd_actions_tracker/tracker.py
wcd_envoyer/contrib/scheduled/__init__.py
wcd_envoyer/contrib/scheduled/admin.py
wcd_envoyer/contrib/scheduled/apps.py
wcd_envoyer/contrib/scheduled/models.py
wcd_envoyer/contrib/scheduled/shortcuts.py
wcd_envoyer/contrib/scheduled/tasks.py
wcd_envoyer/contrib/scheduled/migrations/0001_initial.py
