Metadata-Version: 2.1
Name: wc-django-envoyer
Version: 0.2.16
Summary: Message sender to different channels.
Author: WebCase
Author-email: info@webcase.studio
License: MIT License
Classifier: Development Status :: 2 - Pre-Alpha
Classifier: Programming Language :: Python :: 3
Classifier: Intended Audience :: Developers
Classifier: Topic :: Utilities
Classifier: License :: OSI Approved :: MIT License
Classifier: Operating System :: OS Independent
Requires-Python: >=3.6
License-File: LICENSE
Requires-Dist: django-entangled<0.6.0,>=0.5.4
Requires-Dist: django-jsonfield<2.0.0,>=1.4.1
Requires-Dist: px-django-lingua<0.2.0,>=0.1.7
Requires-Dist: wc-django-notifications<0.4.0,>=0.1.3
Provides-Extra: dev
Requires-Dist: pytest<7.0,>=6.0; extra == "dev"
Requires-Dist: pytest-mock<4.0.0,>=3.10.0; extra == "dev"
Requires-Dist: pytest-watch<5.0,>=4.2; extra == "dev"
Requires-Dist: pytest-django<5.0,>=4.3; extra == "dev"
Requires-Dist: django-environ==0.11.2; extra == "dev"
Requires-Dist: django-stubs; extra == "dev"
Requires-Dist: django<6,>=2.2; extra == "dev"
Requires-Dist: twine; extra == "dev"
